astrotel/__init__.py
astrotel/base.py
astrotel/config.py
astrotel/error.py
astrotel/provider/__init__.py
astrotel/provider/celery.py
astrotel/provider/fastapi.py
astrotel-0.1.0.dist-info/METADATA
astrotel-0.1.0.dist-info/WHEEL
astrotel-0.1.0.dist-info/RECORD
