Metadata-Version: 2.4
Name: astrotel
Version: 0.1.0
Summary: Add your description here
Requires-Python: >=3.12
Requires-Dist: opentelemetry-api>=1.37.0
Requires-Dist: opentelemetry-exporter-otlp-proto-grpc>=1.37.0
Requires-Dist: opentelemetry-exporter-otlp-proto-http>=1.37.0
Requires-Dist: opentelemetry-instrumentation>=0.58b0
Requires-Dist: opentelemetry-sdk>=1.37.0
Requires-Dist: pydantic-settings>=2.10.1
Provides-Extra: fastapi
Requires-Dist: httpx>=0.28.1; extra == 'fastapi'
Requires-Dist: opentelemetry-instrumentation-fastapi>=0.58b0; extra == 'fastapi'
Requires-Dist: opentelemetry-instrumentation-httpx>=0.58b0; extra == 'fastapi'
Requires-Dist: opentelemetry-instrumentation-requests>=0.58b0; extra == 'fastapi'
